eiplgrader/__init__.py
eiplgrader/codegen.py
eiplgrader/tester.py
eiplgrader-0.1.10.dist-info/LICENSE
eiplgrader-0.1.10.dist-info/METADATA
eiplgrader-0.1.10.dist-info/WHEEL
eiplgrader-0.1.10.dist-info/RECORD
